LICENSE
MANIFEST.in
README.md
setup.py
rask/__init__.py
rask.egg-info/PKG-INFO
rask.egg-info/SOURCES.txt
rask.egg-info/dependency_links.txt
rask.egg-info/requires.txt
rask.egg-info/top_level.txt
rask/base/__init__.py
rask/concurrent/__init__.py
rask/concurrent/future_chain.py
rask/http/__init__.py
rask/io/__init__.py
rask/io/utcode/__init__.py
rask/io/utcode/_file.py
rask/io/utcode/tcp.py
rask/ioengine/__init__.py
rask/main/__init__.py
rask/options/__init__.py
rask/parser/__init__.py
rask/parser/bencode/__init__.py
rask/parser/date/__init__.py
rask/parser/json/__init__.py
rask/parser/riak/__init__.py
rask/parser/riak/dict_to_map.py
rask/parser/riak/map_to_dict.py
rask/parser/utcode/__init__.py
rask/raid/__init__.py
rask/raid/client.py
rask/raid/envelop.py
rask/raid/handler.py
rask/raid/msg.py
rask/raid/raid.py
rask/raid/recipes/__init__.py
rask/raid/recipes/c/__init__.py
rask/raid/recipes/c/ping.py
rask/raid/recipes/c/raid_hi.py
rask/raid/recipes/s/__init__.py
rask/raid/recipes/s/ping.py
rask/raid/recipes/s/raid_hi.py
rask/raid/recipes/s/raid_welcome.py
rask/raven/__init__.py
rask/rmq/__init__.py
rask/rmq/ack.py
rask/rmq/announce.py
rask/rmq/channel.py
rask/rmq/connection.py
rask/tcpserver/__init__.py