Metadata-Version: 1.0
Name: rask
Version: 0.1.4
Summary: Viking Makt Framework
Home-page: http://code.umgeher.org/rask
Author: Umgeher Torgersen
Author-email: me@umgeher.org
License: http://code.umgeher.org/fossil.cgi/rask/artifact/3b9a146264aed1f5
Platform: UNKNOWN
